django_ext_utils/__init__.py
django_ext_utils/rest_utils.py
django_ext_utils/utils.py
django_ext_utils-0.0.1.dist-info/LICENSE.txt
django_ext_utils-0.0.1.dist-info/METADATA
django_ext_utils-0.0.1.dist-info/WHEEL
django_ext_utils-0.0.1.dist-info/top_level.txt
django_ext_utils-0.0.1.dist-info/RECORD
