Metadata-Version: 2.1
Name: django-ext-utils
Version: 0.0.1
Summary: Useful utilities for your django project
Home-page: https://github.com/a1k89/django-ext-utils
Author: Andrei Koptev
Author-email: akoptev1989@ya.ru
License: MIT
Keywords: django rest utils
Platform: UNKNOWN
Classifier: Framework :: Django
Classifier: Intended Audience :: Developers
Classifier: Intended Audience :: System Administrators
Classifier: Operating System :: OS Independent
Classifier: Topic :: Software Development
Requires-Dist: Django (>=2.0)
Requires-Dist: Pillow
Provides-Extra: with_rest
Requires-Dist: djangorestframework (>=3.0) ; extra == 'with_rest'
